business_metrics.py
some_cringeHW1-0.0.1.dist-info/METADATA
some_cringeHW1-0.0.1.dist-info/WHEEL
some_cringeHW1-0.0.1.dist-info/entry_points.txt
some_cringeHW1-0.0.1.dist-info/top_level.txt
some_cringeHW1-0.0.1.dist-info/RECORD
