Metadata-Version: 2.1
Name: some_cringeHW1
Version: 0.0.1
Summary: calculate roi
Author: osisochka
Author-email: a.onufrienko@edu.centraluniversity.ru
Requires-Python: >=3.6
